_atoti/__init__.py
_atoti/py.typed
atoti-0.9.12.dist-info/WHEEL
atoti-0.9.12.dist-info/METADATA
atoti-0.9.12.dist-info/RECORD
